gempa_terkini/__init__.py
latestearthquake_indonesia_RBP01-0.4.dist-info/LICENSE
latestearthquake_indonesia_RBP01-0.4.dist-info/METADATA
latestearthquake_indonesia_RBP01-0.4.dist-info/WHEEL
latestearthquake_indonesia_RBP01-0.4.dist-info/top_level.txt
latestearthquake_indonesia_RBP01-0.4.dist-info/RECORD
